autoth/__init__.py
autoth/core.py
autoth_qiuqiangkong-0.0.3.dist-info/LICENSE.MIT
autoth_qiuqiangkong-0.0.3.dist-info/METADATA
autoth_qiuqiangkong-0.0.3.dist-info/WHEEL
autoth_qiuqiangkong-0.0.3.dist-info/top_level.txt
autoth_qiuqiangkong-0.0.3.dist-info/RECORD
