Metadata-Version: 2.1
Name: autoth-qiuqiangkong
Version: 0.0.3
Summary: Automatic threshold optimization
Home-page: https://github.com/qiuqiangkong/autoth
Author: Qiuqiang Kong
Author-email: qiuqiangkong@gmail.com
License: UNKNOWN
Platform: UNKNOWN
Classifier: Programming Language :: Python :: 3
Classifier: License :: OSI Approved :: MIT License
Classifier: Operating System :: OS Independent
Requires-Python: >=3.6
